cppcheck_junit.py
cppcheck_junit-2.4.0.data/scripts/cppcheck_junit.py
cppcheck_junit-2.4.0.dist-info/LICENSE.txt
cppcheck_junit-2.4.0.dist-info/METADATA
cppcheck_junit-2.4.0.dist-info/WHEEL
cppcheck_junit-2.4.0.dist-info/entry_points.txt
cppcheck_junit-2.4.0.dist-info/top_level.txt
cppcheck_junit-2.4.0.dist-info/RECORD
