Metadata-Version: 2.1
Name: cppcheck-junit
Version: 2.4.0
Summary: Converts Cppcheck XML output to JUnit format.
Home-page: https://github.com/johnthagen/cppcheck-junit
Author: John Hagen
Author-email: johnthagen@gmail.com
License: MIT
Keywords: Cppcheck C++ JUnit
Classifier: Development Status :: 5 - Production/Stable
Classifier: Environment :: Console
Classifier: Intended Audience :: Developers
Classifier: License :: OSI Approved :: MIT License
Classifier: Operating System :: OS Independent
Classifier: Programming Language :: C++
Classifier: Programming Language :: Python
Classifier: Programming Language :: Python :: 3
Classifier: Programming Language :: Python :: 3 :: Only
Classifier: Programming Language :: Python :: 3.8
Classifier: Programming Language :: Python :: 3.9
Classifier: Programming Language :: Python :: 3.10
Classifier: Programming Language :: Python :: 3.11
Classifier: Programming Language :: Python :: 3.12
Classifier: Topic :: Software Development :: Quality Assurance
Requires-Python: >=3.8
License-File: LICENSE.txt
Requires-Dist: exitstatus >=1.0.0
Requires-Dist: junitparser >=3.0.0
